<Atlas><Texture filename="crafting_menu_avatars.tex" /><Elements><Element name="avatar_mod.tex" u1="0.000244140625" u2="0.124755859375" v1="0.75048828125" v2="0.99951171875" /><Element name="avatar_winona.tex" u1="0.625244140625" u2="0.749755859375" v1="0.50048828125" v2="0.74951171875" /><Element name="avatar_wolfgang.tex" u1="0.750244140625" u2="0.874755859375" v1="0.50048828125" v2="0.74951171875" /><Element name="avatar_wickerbottom.tex" u1="0.250244140625" u2="0.374755859375" v1="0.50048828125" v2="0.74951171875" /><Element name="avatar_wanda.tex" u1="0.375244140625" u2="0.499755859375" v1="0.75048828125" v2="0.99951171875" /><Element name="avatar_woodie_2.tex" u1="0.250244140625" u2="0.374755859375" v1="0.25048828125" v2="0.49951171875" /><Element name="avatar_warly.tex" u1="0.500244140625" u2="0.624755859375" v1="0.75048828125" v2="0.99951171875" /><Element name="avatar_wathgrithr.tex" u1="0.625244140625" u2="0.749755859375" v1="0.75048828125" v2="0.99951171875" /><Element name="avatar_wonkey.tex" u1="0.875244140625" u2="0.999755859375" v1="0.50048828125" v2="0.74951171875" /><Element name="avatar_willow.tex" u1="0.375244140625" u2="0.499755859375" v1="0.50048828125" v2="0.74951171875" /><Element name="avatar_woodie.tex" u1="0.000244140625" u2="0.124755859375" v1="0.25048828125" v2="0.49951171875" /><Element name="avatar_wormwood_3.tex" u1="0.875244140625" u2="0.999755859375" v1="0.25048828125" v2="0.49951171875" /><Element name="avatar_wormwood_1.tex" u1="0.625244140625" u2="0.749755859375" v1="0.25048828125" v2="0.49951171875" /><Element name="avatar_wagstaff_npc.tex" u1="0.125244140625" u2="0.249755859375" v1="0.75048828125" v2="0.99951171875" /><Element name="avatar_waxwell.tex" u1="0.750244140625" u2="0.874755859375" v1="0.75048828125" v2="0.99951171875" /><Element name="avatar_webber.tex" u1="0.875244140625" u2="0.999755859375" v1="0.75048828125" v2="0.99951171875" /><Element name="avatar_woodie_1.tex" u1="0.125244140625" u2="0.249755859375" v1="0.25048828125" v2="0.49951171875" /><Element name="avatar_wormwood.tex" u1="0.500244140625" u2="0.624755859375" v1="0.25048828125" v2="0.49951171875" /><Element name="avatar_woodie_3.tex" u1="0.375244140625" u2="0.499755859375" v1="0.25048828125" v2="0.49951171875" /><Element name="avatar_walter.tex" u1="0.250244140625" u2="0.374755859375" v1="0.75048828125" v2="0.99951171875" /><Element name="avatar_wendy.tex" u1="0.000244140625" u2="0.124755859375" v1="0.50048828125" v2="0.74951171875" /><Element name="avatar_wurt.tex" u1="0.125244140625" u2="0.249755859375" v1="0.00048828125" v2="0.24951171875" /><Element name="avatar_wes.tex" u1="0.125244140625" u2="0.249755859375" v1="0.50048828125" v2="0.74951171875" /><Element name="avatar_wx78.tex" u1="0.250244140625" u2="0.374755859375" v1="0.00048828125" v2="0.24951171875" /><Element name="avatar_wilson.tex" u1="0.500244140625" u2="0.624755859375" v1="0.50048828125" v2="0.74951171875" /><Element name="avatar_wortox.tex" u1="0.000244140625" u2="0.124755859375" v1="0.00048828125" v2="0.24951171875" /><Element name="avatar_wormwood_2.tex" u1="0.750244140625" u2="0.874755859375" v1="0.25048828125" v2="0.49951171875" /></Elements></Atlas>