<Atlas><Texture filename="quagmire_food_common_inv_images_hires.tex" /><Elements><Element name="goop_plate.tex" u1="0.25048828125" u2="0.49951171875" v1="0.0009765625" v2="0.4990234375" /><Element name="bowl.tex" u1="0.00048828125" u2="0.24951171875" v1="0.5009765625" v2="0.9990234375" /><Element name="goop_bowl.tex" u1="0.00048828125" u2="0.24951171875" v1="0.0009765625" v2="0.4990234375" /><Element name="plate_silver.tex" u1="0.75048828125" u2="0.99951171875" v1="0.0009765625" v2="0.4990234375" /><Element name="plate.tex" u1="0.50048828125" u2="0.74951171875" v1="0.0009765625" v2="0.4990234375" /><Element name="bowl_silver.tex" u1="0.25048828125" u2="0.49951171875" v1="0.5009765625" v2="0.9990234375" /><Element name="burnt_plate.tex" u1="0.75048828125" u2="0.99951171875" v1="0.5009765625" v2="0.9990234375" /><Element name="burnt_bowl.tex" u1="0.50048828125" u2="0.74951171875" v1="0.5009765625" v2="0.9990234375" /></Elements></Atlas>